dicalum/DclCamera.py
dicalum/DclExif.py
dicalum/DclGui.py
dicalum/DclPlot.py
dicalum/RawRead.py
dicalum/SetVig.py
dicalum/__init__.py
dicalum/coeffs.py
dicalum-4.0b6.dist-info/DESCRIPTION.rst
dicalum-4.0b6.dist-info/METADATA
dicalum-4.0b6.dist-info/RECORD
dicalum-4.0b6.dist-info/WHEEL
dicalum-4.0b6.dist-info/metadata.json
dicalum-4.0b6.dist-info/top_level.txt
